{
  "round": 12,
  "candidates": [
    {
      "name": "P. ABDUL SAMED",
      "party": "Dravida Munnetra Kazhagam",
      "evm_votes": 29061,
      "postal_votes": 2305,
      "total_votes": 31366
    },
    {
      "name": "M. ARUNAGIRI",
      "party": "Naam Tamilar Katchi",
      "evm_votes": 4443,
      "postal_votes": 395,
      "total_votes": 4838
    },
    {
      "name": "DR. PL. VIJAYAKUMAR",
      "party": "All India Anna Dravida Munnetra Kazhagam",
      "evm_votes": 31674,
      "postal_votes": 3348,
      "total_votes": 35022
    },
    {
      "name": "AROCKIARAJ .A",
      "party": "Samaniya Makkal Nala Katchi",
      "evm_votes": 290,
      "postal_votes": 27,
      "total_votes": 317
    },
    {
      "name": "R. KATHIRAVAN",
      "party": "Tamilaga Vettri Kazhagam",
      "evm_votes": 39860,
      "postal_votes": 3208,
      "total_votes": 43068
    },
    {
      "name": "P. MEENA",
      "party": "Puthiya Tamilagam",
      "evm_votes": 118,
      "postal_votes": 7,
      "total_votes": 125
    },
    {
      "name": "RAJAVARMAN .R",
      "party": "Tamizhaga Vaazhvurimai Katchi",
      "evm_votes": 73,
      "postal_votes": 6,
      "total_votes": 79
    },
    {
      "name": "A. RAMAN",
      "party": "Independent",
      "evm_votes": 42,
      "postal_votes": 10,
      "total_votes": 52
    },
    {
      "name": "KATHIRAVAN .M",
      "party": "Independent",
      "evm_votes": 81,
      "postal_votes": 10,
      "total_votes": 91
    },
    {
      "name": "M. KARUPPAN",
      "party": "Independent",
      "evm_votes": 107,
      "postal_votes": 8,
      "total_votes": 115
    },
    {
      "name": "KUTTAIAN",
      "party": "Independent",
      "evm_votes": 56,
      "postal_votes": 6,
      "total_votes": 62
    },
    {
      "name": "SARPHUDIN",
      "party": "Independent",
      "evm_votes": 142,
      "postal_votes": 12,
      "total_votes": 154
    },
    {
      "name": "P. CHINNAN",
      "party": "Independent",
      "evm_votes": 62,
      "postal_votes": 3,
      "total_votes": 65
    },
    {
      "name": "A. SENTHIL KUMAR",
      "party": "Independent",
      "evm_votes": 122,
      "postal_votes": 10,
      "total_votes": 132
    },
    {
      "name": "PERIYAKKA",
      "party": "Independent",
      "evm_votes": 140,
      "postal_votes": 8,
      "total_votes": 148
    },
    {
      "name": "RAJESH .M",
      "party": "Independent",
      "evm_votes": 235,
      "postal_votes": 22,
      "total_votes": 257
    },
    {
      "name": "P. VIJAYAKUMAR",
      "party": "Independent",
      "evm_votes": 269,
      "postal_votes": 22,
      "total_votes": 291
    },
    {
      "name": "M. VIJAYA KUMAR",
      "party": "Independent",
      "evm_votes": 56,
      "postal_votes": 8,
      "total_votes": 64
    },
    {
      "name": "NOTA",
      "party": "None of the Above",
      "evm_votes": 411,
      "postal_votes": 40,
      "total_votes": 451
    }
  ]
}