{
  "round": 23,
  "candidates": [
    {
      "name": "APPAVU.M",
      "party": "Dravida Munnetra Kazhagam",
      "evm_votes": 52898,
      "postal_votes": 2819,
      "total_votes": 55717
    },
    {
      "name": "ESSAKKIAMMAL.E",
      "party": "Bahujan Samaj Party",
      "evm_votes": 302,
      "postal_votes": 21,
      "total_votes": 323
    },
    {
      "name": "GIRIJA THAMARAIPANDIAN.D",
      "party": "Naam Tamilar Katchi",
      "evm_votes": 14306,
      "postal_votes": 694,
      "total_votes": 15000
    },
    {
      "name": "BALAKRISHNAN.S.P",
      "party": "Bharatiya Janata Party",
      "evm_votes": 49233,
      "postal_votes": 1966,
      "total_votes": 51199
    },
    {
      "name": "DR.SATHISH CHRISTOPHER",
      "party": "Tamilaga Vettri Kazhagam",
      "evm_votes": 63166,
      "postal_votes": 4383,
      "total_votes": 67549
    },
    {
      "name": "JESURAJENDRAN.J",
      "party": "Naam Indiar Party",
      "evm_votes": 142,
      "postal_votes": 17,
      "total_votes": 159
    },
    {
      "name": "MAHALAKSHMI",
      "party": "Puthiya Makkal Tamil Desam Katchi",
      "evm_votes": 91,
      "postal_votes": 6,
      "total_votes": 97
    },
    {
      "name": "MURUGAN.P",
      "party": "Thamizhaka Padaippalar Makkal Katchi",
      "evm_votes": 102,
      "postal_votes": 7,
      "total_votes": 109
    },
    {
      "name": "ARUNRAJ",
      "party": "Independent",
      "evm_votes": 33,
      "postal_votes": 1,
      "total_votes": 34
    },
    {
      "name": "OLIVER ANTON NAVAMONI. S",
      "party": "Independent",
      "evm_votes": 64,
      "postal_votes": 5,
      "total_votes": 69
    },
    {
      "name": "ANANTHI.R",
      "party": "Independent",
      "evm_votes": 71,
      "postal_votes": 5,
      "total_votes": 76
    },
    {
      "name": "ANAND PRASAD",
      "party": "Independent",
      "evm_votes": 181,
      "postal_votes": 10,
      "total_votes": 191
    },
    {
      "name": "KARTHICK.V",
      "party": "Independent",
      "evm_votes": 197,
      "postal_votes": 16,
      "total_votes": 213
    },
    {
      "name": "KINGSLY ISACC JEBARAJ.S",
      "party": "Independent",
      "evm_votes": 124,
      "postal_votes": 6,
      "total_votes": 130
    },
    {
      "name": "SUNDARAJAN.S",
      "party": "Independent",
      "evm_votes": 86,
      "postal_votes": 5,
      "total_votes": 91
    },
    {
      "name": "SELVAN.T",
      "party": "Independent",
      "evm_votes": 257,
      "postal_votes": 16,
      "total_votes": 273
    },
    {
      "name": "DANIEL.A",
      "party": "Independent",
      "evm_votes": 763,
      "postal_votes": 42,
      "total_votes": 805
    },
    {
      "name": "PON SANTHANA KUMARAN.R",
      "party": "Independent",
      "evm_votes": 439,
      "postal_votes": 26,
      "total_votes": 465
    },
    {
      "name": "MANIKANDAN.A.I",
      "party": "Independent",
      "evm_votes": 145,
      "postal_votes": 12,
      "total_votes": 157
    },
    {
      "name": "MANIKANDAN.S",
      "party": "Independent",
      "evm_votes": 194,
      "postal_votes": 7,
      "total_votes": 201
    },
    {
      "name": "MANIKANDAN.L",
      "party": "Independent",
      "evm_votes": 192,
      "postal_votes": 24,
      "total_votes": 216
    },
    {
      "name": "RAJAN.P",
      "party": "Independent",
      "evm_votes": 47,
      "postal_votes": 4,
      "total_votes": 51
    },
    {
      "name": "JEYARAJ.P V S",
      "party": "Independent",
      "evm_votes": 90,
      "postal_votes": 1,
      "total_votes": 91
    },
    {
      "name": "NOTA",
      "party": "None of the Above",
      "evm_votes": 441,
      "postal_votes": 16,
      "total_votes": 457
    }
  ]
}