{
  "round": 8,
  "candidates": [
    {
      "name": "P. KRISHNASAMY",
      "party": "Bahujan Samaj Party",
      "evm_votes": 112,
      "postal_votes": 11,
      "total_votes": 123
    },
    {
      "name": "DURAI. SENTHAMIL SELVAN B.E",
      "party": "Dravida Munnetra Kazhagam",
      "evm_votes": 20170,
      "postal_votes": 3287,
      "total_votes": 23457
    },
    {
      "name": "NARMADHA. G.",
      "party": "Naam Tamilar Katchi",
      "evm_votes": 2814,
      "postal_votes": 346,
      "total_votes": 3160
    },
    {
      "name": "VANATHI SRINIVASAN",
      "party": "Bharatiya Janata Party",
      "evm_votes": 16950,
      "postal_votes": 1837,
      "total_votes": 18787
    },
    {
      "name": "K. UDHAYAKUMAR",
      "party": "Thamizhaka Padaippalar Makkal Katchi",
      "evm_votes": 112,
      "postal_votes": 10,
      "total_votes": 122
    },
    {
      "name": "V. SAMPATHKUMAR",
      "party": "Tamilaga Vettri Kazhagam",
      "evm_votes": 26103,
      "postal_votes": 3721,
      "total_votes": 29824
    },
    {
      "name": "S. SENTHILKUMAR",
      "party": "Samaniya Makkal Nala Katchi",
      "evm_votes": 40,
      "postal_votes": 4,
      "total_votes": 44
    },
    {
      "name": "S. MEENAKSHI SUNDARAM",
      "party": "Tamizhaga Murpokku Makkal Katchi",
      "evm_votes": 22,
      "postal_votes": 6,
      "total_votes": 28
    },
    {
      "name": "K. RAGHUL GANDHI",
      "party": "All India Puratchi Thalaivar Makkal Munnettra Kazhagam",
      "evm_votes": 33,
      "postal_votes": 9,
      "total_votes": 42
    },
    {
      "name": "RAJASEKARAN. B.",
      "party": "Tamizhaga Vaazhvurimai Katchi",
      "evm_votes": 45,
      "postal_votes": 5,
      "total_votes": 50
    },
    {
      "name": "G.D. KRISHNAKUMAR",
      "party": "Independent",
      "evm_votes": 30,
      "postal_votes": 2,
      "total_votes": 32
    },
    {
      "name": "V. KRISHNAN",
      "party": "Independent",
      "evm_votes": 39,
      "postal_votes": 9,
      "total_votes": 48
    },
    {
      "name": "R. SATHISH KUMAR",
      "party": "Independent",
      "evm_votes": 17,
      "postal_votes": 4,
      "total_votes": 21
    },
    {
      "name": "K. SAMPATH KUMAR",
      "party": "Independent",
      "evm_votes": 21,
      "postal_votes": 1,
      "total_votes": 22
    },
    {
      "name": "S. SAMPATHKUMAR",
      "party": "Independent",
      "evm_votes": 47,
      "postal_votes": 2,
      "total_votes": 49
    },
    {
      "name": "R. SAMPATH KUMAR",
      "party": "Independent",
      "evm_votes": 98,
      "postal_votes": 10,
      "total_votes": 108
    },
    {
      "name": "P. SARAVANAN",
      "party": "Independent",
      "evm_votes": 39,
      "postal_votes": 6,
      "total_votes": 45
    },
    {
      "name": "A.K. SENTHAMIZH SELVAN",
      "party": "Independent",
      "evm_votes": 95,
      "postal_votes": 25,
      "total_votes": 120
    },
    {
      "name": "R. SETHURAGUNATHAN",
      "party": "Independent",
      "evm_votes": 20,
      "postal_votes": 3,
      "total_votes": 23
    },
    {
      "name": "S. DHANA RAJ",
      "party": "Independent",
      "evm_votes": 33,
      "postal_votes": 4,
      "total_votes": 37
    },
    {
      "name": "PALANIKUMAR. V.",
      "party": "Independent",
      "evm_votes": 39,
      "postal_votes": 4,
      "total_votes": 43
    },
    {
      "name": "BALU. P.M.",
      "party": "Independent",
      "evm_votes": 82,
      "postal_votes": 11,
      "total_votes": 93
    },
    {
      "name": "R. MANIAN",
      "party": "Independent",
      "evm_votes": 25,
      "postal_votes": 4,
      "total_votes": 29
    },
    {
      "name": "A. MARIMUTHU",
      "party": "Independent",
      "evm_votes": 17,
      "postal_votes": 1,
      "total_votes": 18
    },
    {
      "name": "A. RAMESH",
      "party": "Independent",
      "evm_votes": 8,
      "postal_votes": 0,
      "total_votes": 8
    },
    {
      "name": "RAVI. V",
      "party": "Independent",
      "evm_votes": 33,
      "postal_votes": 2,
      "total_votes": 35
    },
    {
      "name": "G. RAJKUMAR",
      "party": "Independent",
      "evm_votes": 10,
      "postal_votes": 1,
      "total_votes": 11
    },
    {
      "name": "V. LINGARAJA",
      "party": "Independent",
      "evm_votes": 16,
      "postal_votes": 2,
      "total_votes": 18
    },
    {
      "name": "NOTA",
      "party": "None of the Above",
      "evm_votes": 372,
      "postal_votes": 49,
      "total_votes": 421
    }
  ]
}