{
  "round": 1,
  "candidates": [
    {
      "name": "KARMEGAN.M",
      "party": "Naam Tamilar Katchi",
      "evm_votes": 0,
      "postal_votes": 325,
      "total_votes": 325
    },
    {
      "name": "M.P.SAMINATHAN",
      "party": "Dravida Munnetra Kazhagam",
      "evm_votes": 0,
      "postal_votes": 2473,
      "total_votes": 2473
    },
    {
      "name": "NSN NATARAJ",
      "party": "All India Anna Dravida Munnetra Kazhagam",
      "evm_votes": 0,
      "postal_votes": 3027,
      "total_votes": 3027
    },
    {
      "name": "P.THIRUGNANASAMBANTHAM",
      "party": "Party for the Rights of Other backward Classes",
      "evm_votes": 0,
      "postal_votes": 23,
      "total_votes": 23
    },
    {
      "name": "MANI GOUNDER",
      "party": "Tamilaga Vettri Kazhagam",
      "evm_votes": 0,
      "postal_votes": 3520,
      "total_votes": 3520
    },
    {
      "name": "R.VIJAYALAKSHMI",
      "party": "Ganasangam Party of India",
      "evm_votes": 0,
      "postal_votes": 3,
      "total_votes": 3
    },
    {
      "name": "K.ARUMUGAM",
      "party": "Independent",
      "evm_votes": 0,
      "postal_votes": 2,
      "total_votes": 2
    },
    {
      "name": "R. IMMANUVEL",
      "party": "Independent",
      "evm_votes": 0,
      "postal_votes": 5,
      "total_votes": 5
    },
    {
      "name": "KARTHIKEYAN",
      "party": "Independent",
      "evm_votes": 0,
      "postal_votes": 8,
      "total_votes": 8
    },
    {
      "name": "GOWTHAM",
      "party": "Independent",
      "evm_votes": 0,
      "postal_votes": 3,
      "total_votes": 3
    },
    {
      "name": "T.NATARAJ",
      "party": "Independent",
      "evm_votes": 0,
      "postal_votes": 1,
      "total_votes": 1
    },
    {
      "name": "PALANISAMY",
      "party": "Independent",
      "evm_votes": 0,
      "postal_votes": 3,
      "total_votes": 3
    },
    {
      "name": "P.PARTHIBAN",
      "party": "Independent",
      "evm_votes": 0,
      "postal_votes": 13,
      "total_votes": 13
    },
    {
      "name": "P.MANI",
      "party": "Independent",
      "evm_votes": 0,
      "postal_votes": 10,
      "total_votes": 10
    },
    {
      "name": "B.RAJENDRAN",
      "party": "Independent",
      "evm_votes": 0,
      "postal_votes": 10,
      "total_votes": 10
    },
    {
      "name": "NOTA",
      "party": "None of the Above",
      "evm_votes": 0,
      "postal_votes": 28,
      "total_votes": 28
    }
  ]
}