{
  "round": 10,
  "candidates": [
    {
      "name": "KANNAN KA.SO.KA.",
      "party": "Dravida Munnetra Kazhagam",
      "evm_votes": 25721,
      "postal_votes": 3052,
      "total_votes": 28773
    },
    {
      "name": "CHINNADURAI S.",
      "party": "Bahujan Samaj Party",
      "evm_votes": 183,
      "postal_votes": 16,
      "total_votes": 199
    },
    {
      "name": "REVATHI K.",
      "party": "Naam Tamilar Katchi",
      "evm_votes": 2391,
      "postal_votes": 259,
      "total_votes": 2650
    },
    {
      "name": "AZHAGESAN V.R.",
      "party": "Desiya Makkal Sakthi Katchi",
      "evm_votes": 49,
      "postal_votes": 5,
      "total_votes": 54
    },
    {
      "name": "RAVANAN M.",
      "party": "Naadaalum Makkal Katchi",
      "evm_votes": 286,
      "postal_votes": 31,
      "total_votes": 317
    },
    {
      "name": "KAVITHA RAJENDRAN G.",
      "party": "Tamilaga Vettri Kazhagam",
      "evm_votes": 22099,
      "postal_votes": 2145,
      "total_votes": 24244
    },
    {
      "name": "SANKAR M.",
      "party": "Rashtriya Samaj Dal (R)",
      "evm_votes": 231,
      "postal_votes": 47,
      "total_votes": 278
    },
    {
      "name": "PAGUTHARIVALAN A.",
      "party": "Tamizhaga Vaazhvurimai Katchi",
      "evm_votes": 113,
      "postal_votes": 36,
      "total_votes": 149
    },
    {
      "name": "RAVISANKAR N.",
      "party": "Aanaithinthiya Jananayaka Pathukappu Kazhagam",
      "evm_votes": 499,
      "postal_votes": 209,
      "total_votes": 708
    },
    {
      "name": "VAITHILINGAM G.",
      "party": "Pattali Makkal Katchi",
      "evm_votes": 34186,
      "postal_votes": 3842,
      "total_votes": 38028
    },
    {
      "name": "JAYABALAN G.",
      "party": "Vada Tamil Nadu Munnetra Katchi",
      "evm_votes": 181,
      "postal_votes": 20,
      "total_votes": 201
    },
    {
      "name": "ANANDHAKUMAR R.",
      "party": "Independent",
      "evm_votes": 238,
      "postal_votes": 30,
      "total_votes": 268
    },
    {
      "name": "ISAC NEWTAN J.",
      "party": "Independent",
      "evm_votes": 46,
      "postal_votes": 2,
      "total_votes": 48
    },
    {
      "name": "KANNAN K.",
      "party": "Independent",
      "evm_votes": 60,
      "postal_votes": 8,
      "total_votes": 68
    },
    {
      "name": "GURUNATHAN N.",
      "party": "Independent",
      "evm_votes": 75,
      "postal_votes": 14,
      "total_votes": 89
    },
    {
      "name": "CHANTHIRASEKAR S.",
      "party": "Independent",
      "evm_votes": 375,
      "postal_votes": 48,
      "total_votes": 423
    },
    {
      "name": "VINOTHSAVARIREMIJEAS C.",
      "party": "Independent",
      "evm_votes": 238,
      "postal_votes": 30,
      "total_votes": 268
    },
    {
      "name": "VENKATAJALAPATHI R.",
      "party": "Independent",
      "evm_votes": 15,
      "postal_votes": 3,
      "total_votes": 18
    },
    {
      "name": "VEZHAVENTHAN D.",
      "party": "Independent",
      "evm_votes": 16,
      "postal_votes": 3,
      "total_votes": 19
    },
    {
      "name": "NOTA",
      "party": "None of the Above",
      "evm_votes": 133,
      "postal_votes": 18,
      "total_votes": 151
    }
  ]
}