{
  "round": 22,
  "candidates": [
    {
      "name": "ASHOKKUMAR.K",
      "party": "All India Anna Dravida Munnetra Kazhagam",
      "evm_votes": 58657,
      "postal_votes": 2492,
      "total_votes": 61149
    },
    {
      "name": "SIVAKUMAR.S",
      "party": "Bahujan Samaj Party",
      "evm_votes": 517,
      "postal_votes": 14,
      "total_votes": 531
    },
    {
      "name": "SUGANTHI",
      "party": "Naam Tamilar Katchi",
      "evm_votes": 5243,
      "postal_votes": 203,
      "total_votes": 5446
    },
    {
      "name": "CHELLAKUMAR.A",
      "party": "Indian National Congress",
      "evm_votes": 50394,
      "postal_votes": 2245,
      "total_votes": 52639
    },
    {
      "name": "SINGARAVELAN VISWANATHAN",
      "party": "Vishwa Tamil Kazhagam",
      "evm_votes": 450,
      "postal_votes": 19,
      "total_votes": 469
    },
    {
      "name": "MANGAMMAL",
      "party": "Tamilar Makkal Katchi",
      "evm_votes": 299,
      "postal_votes": 5,
      "total_votes": 304
    },
    {
      "name": "MUKUNDHAN.P",
      "party": "Tamilaga Vettri Kazhagam",
      "evm_votes": 77798,
      "postal_votes": 3097,
      "total_votes": 80895
    },
    {
      "name": "MUTHULAKSHMI VEERAPPAN",
      "party": "Tamizhaga Vaazhvurimai Katchi",
      "evm_votes": 314,
      "postal_votes": 11,
      "total_votes": 325
    },
    {
      "name": "ADVOCATE.MUTHAIAH.S.",
      "party": "Thakkam Katchi",
      "evm_votes": 139,
      "postal_votes": 1,
      "total_votes": 140
    },
    {
      "name": "KUMARESAN.M",
      "party": "Independent",
      "evm_votes": 133,
      "postal_votes": 4,
      "total_votes": 137
    },
    {
      "name": "CHANDRAMOHAN.K.M.",
      "party": "Independent",
      "evm_votes": 132,
      "postal_votes": 2,
      "total_votes": 134
    },
    {
      "name": "SIVAN.C",
      "party": "Independent",
      "evm_votes": 240,
      "postal_votes": 9,
      "total_votes": 249
    },
    {
      "name": "SRINIVASAN.K",
      "party": "Independent",
      "evm_votes": 197,
      "postal_votes": 12,
      "total_votes": 209
    },
    {
      "name": "NANJUNDAN.M",
      "party": "Independent",
      "evm_votes": 121,
      "postal_votes": 4,
      "total_votes": 125
    },
    {
      "name": "VENKATESHRAJA.E",
      "party": "Independent",
      "evm_votes": 139,
      "postal_votes": 7,
      "total_votes": 146
    },
    {
      "name": "NOTA",
      "party": "None of the Above",
      "evm_votes": 941,
      "postal_votes": 41,
      "total_votes": 982
    }
  ]
}