{
  "round": 19,
  "candidates": [
    {
      "name": "UDHAYASURIYAN T",
      "party": "Dravida Munnetra Kazhagam",
      "evm_votes": 57142,
      "postal_votes": 3667,
      "total_votes": 60809
    },
    {
      "name": "SUDHA M",
      "party": "Bahujan Samaj Party",
      "evm_votes": 402,
      "postal_votes": 23,
      "total_votes": 425
    },
    {
      "name": "RAMESH K",
      "party": "Naam Tamilar Katchi",
      "evm_votes": 3939,
      "postal_votes": 261,
      "total_votes": 4200
    },
    {
      "name": "RAKESH R",
      "party": "All India Anna Dravida Munnetra Kazhagam",
      "evm_votes": 58672,
      "postal_votes": 2312,
      "total_votes": 60984
    },
    {
      "name": "RAMACHANDIRAN M",
      "party": "Tamizhaga Vaazhvurimai Katchi",
      "evm_votes": 538,
      "postal_votes": 10,
      "total_votes": 548
    },
    {
      "name": "GANGASEKAR A",
      "party": "MAKKAL SAKTHI KATCHI",
      "evm_votes": 152,
      "postal_votes": 6,
      "total_votes": 158
    },
    {
      "name": "SANNIYASI N",
      "party": "Veerath Thiyagi Viswanathadoss Thozhilalarkal Katchi",
      "evm_votes": 77,
      "postal_votes": 4,
      "total_votes": 81
    },
    {
      "name": "NADARAJAN K",
      "party": "All India Puratchi Thalaivar Makkal Munnettra Kazhagam",
      "evm_votes": 248,
      "postal_votes": 17,
      "total_votes": 265
    },
    {
      "name": "JAGADESAN A",
      "party": "Tamilaga Vettri Kazhagam",
      "evm_votes": 49184,
      "postal_votes": 3369,
      "total_votes": 52553
    },
    {
      "name": "ANBAZHAGAN S",
      "party": "Independent",
      "evm_votes": 76,
      "postal_votes": 8,
      "total_votes": 84
    },
    {
      "name": "KAVIKUIL V",
      "party": "Independent",
      "evm_votes": 77,
      "postal_votes": 6,
      "total_votes": 83
    },
    {
      "name": "SAMIKKANNU M",
      "party": "Independent",
      "evm_votes": 95,
      "postal_votes": 3,
      "total_votes": 98
    },
    {
      "name": "DURAI EZHILAN P",
      "party": "Independent",
      "evm_votes": 251,
      "postal_votes": 7,
      "total_votes": 258
    },
    {
      "name": "PACHAIYAPPAN K",
      "party": "Independent",
      "evm_votes": 281,
      "postal_votes": 13,
      "total_votes": 294
    },
    {
      "name": "MANI G",
      "party": "Independent",
      "evm_votes": 134,
      "postal_votes": 7,
      "total_votes": 141
    },
    {
      "name": "MANIKANDAN P",
      "party": "Independent",
      "evm_votes": 475,
      "postal_votes": 32,
      "total_votes": 507
    },
    {
      "name": "MAYILAMPARAI MARI A",
      "party": "Independent",
      "evm_votes": 428,
      "postal_votes": 11,
      "total_votes": 439
    },
    {
      "name": "DR.MURUGU K",
      "party": "Independent",
      "evm_votes": 85,
      "postal_votes": 3,
      "total_votes": 88
    },
    {
      "name": "VIGNESH R",
      "party": "Independent",
      "evm_votes": 72,
      "postal_votes": 2,
      "total_votes": 74
    },
    {
      "name": "VIJAY J",
      "party": "Independent",
      "evm_votes": 321,
      "postal_votes": 10,
      "total_votes": 331
    },
    {
      "name": "JAYAPRAKASH K",
      "party": "Independent",
      "evm_votes": 92,
      "postal_votes": 3,
      "total_votes": 95
    },
    {
      "name": "HARUN RASHEETH J",
      "party": "Independent",
      "evm_votes": 65,
      "postal_votes": 2,
      "total_votes": 67
    },
    {
      "name": "NOTA",
      "party": "None of the Above",
      "evm_votes": 272,
      "postal_votes": 16,
      "total_votes": 288
    }
  ]
}