{
  "round": 13,
  "candidates": [
    {
      "name": "S. KARTHIGAISELVAN",
      "party": "Bahujan Samaj Party",
      "evm_votes": 305,
      "postal_votes": 22,
      "total_votes": 327
    },
    {
      "name": "DR. A. SIMON JUSTIN",
      "party": "Naam Tamilar Katchi",
      "evm_votes": 4761,
      "postal_votes": 301,
      "total_votes": 5062
    },
    {
      "name": "I. PERIASAMY",
      "party": "Dravida Munnetra Kazhagam",
      "evm_votes": 52149,
      "postal_votes": 3458,
      "total_votes": 55607
    },
    {
      "name": "A. VISWANATHAN",
      "party": "All India Anna Dravida Munnetra Kazhagam",
      "evm_votes": 18227,
      "postal_votes": 1400,
      "total_votes": 19627
    },
    {
      "name": "N. KALAISELVI",
      "party": "Tamilaga Vettri Kazhagam",
      "evm_votes": 39735,
      "postal_votes": 2843,
      "total_votes": 42578
    },
    {
      "name": "D. SANKAR",
      "party": "Naadaalum Makkal Katchi",
      "evm_votes": 434,
      "postal_votes": 29,
      "total_votes": 463
    },
    {
      "name": "M.K. NAGENDRAN",
      "party": "Aanaithinthiya Jananayaka Pathukappu Kazhagam",
      "evm_votes": 282,
      "postal_votes": 20,
      "total_votes": 302
    },
    {
      "name": "S. BALA MURUGAN",
      "party": "Tamizhaga Vaazhvurimai Katchi",
      "evm_votes": 71,
      "postal_votes": 5,
      "total_votes": 76
    },
    {
      "name": "K. JAYAPRAKASH",
      "party": "Puthiya Tamilagam",
      "evm_votes": 103,
      "postal_votes": 8,
      "total_votes": 111
    },
    {
      "name": "K. KATHIRESAN",
      "party": "Independent",
      "evm_votes": 107,
      "postal_votes": 6,
      "total_votes": 113
    },
    {
      "name": "D. NAGARAJ",
      "party": "Independent",
      "evm_votes": 94,
      "postal_votes": 5,
      "total_votes": 99
    },
    {
      "name": "M. PERIYASAMY",
      "party": "Independent",
      "evm_votes": 143,
      "postal_votes": 4,
      "total_votes": 147
    },
    {
      "name": "P. MANIVEL",
      "party": "Independent",
      "evm_votes": 224,
      "postal_votes": 11,
      "total_votes": 235
    },
    {
      "name": "K. VISVANATHAN",
      "party": "Independent",
      "evm_votes": 343,
      "postal_votes": 19,
      "total_votes": 362
    },
    {
      "name": "K. VELMURUGAN",
      "party": "Independent",
      "evm_votes": 60,
      "postal_votes": 2,
      "total_votes": 62
    },
    {
      "name": "NOTA",
      "party": "None of the Above",
      "evm_votes": 366,
      "postal_votes": 28,
      "total_votes": 394
    }
  ]
}