{
  "round": 13,
  "candidates": [
    {
      "name": "ANUSHA V",
      "party": "Naam Tamilar Katchi",
      "evm_votes": 3149,
      "postal_votes": 168,
      "total_votes": 3317
    },
    {
      "name": "SATHIYANARAYANAN B",
      "party": "All India Anna Dravida Munnetra Kazhagam",
      "evm_votes": 24475,
      "postal_votes": 2152,
      "total_votes": 26627
    },
    {
      "name": "RAJA ANBAZHAGAN",
      "party": "Dravida Munnetra Kazhagam",
      "evm_votes": 26313,
      "postal_votes": 1160,
      "total_votes": 27473
    },
    {
      "name": "ANAND N",
      "party": "Tamilaga Vettri Kazhagam",
      "evm_votes": 37034,
      "postal_votes": 1862,
      "total_votes": 38896
    },
    {
      "name": "RAVI M L",
      "party": "Desiya Makkal Sakthi Katchi",
      "evm_votes": 77,
      "postal_votes": 4,
      "total_votes": 81
    },
    {
      "name": "ABUKITHER M",
      "party": "Independent",
      "evm_votes": 88,
      "postal_votes": 1,
      "total_votes": 89
    },
    {
      "name": "ARAVIND GOSH Y T",
      "party": "Independent",
      "evm_votes": 19,
      "postal_votes": 0,
      "total_votes": 19
    },
    {
      "name": "EASAN NATARAJAN T",
      "party": "Independent",
      "evm_votes": 27,
      "postal_votes": 5,
      "total_votes": 32
    },
    {
      "name": "KUMAR SRI SRI B",
      "party": "Independent",
      "evm_votes": 17,
      "postal_votes": 0,
      "total_votes": 17
    },
    {
      "name": "SATHISH KUMAR B",
      "party": "Independent",
      "evm_votes": 17,
      "postal_votes": 1,
      "total_votes": 18
    },
    {
      "name": "GNANASEKARAN G",
      "party": "Independent",
      "evm_votes": 24,
      "postal_votes": 0,
      "total_votes": 24
    },
    {
      "name": "THENNARASU P",
      "party": "Independent",
      "evm_votes": 7,
      "postal_votes": 1,
      "total_votes": 8
    },
    {
      "name": "PADMINI NARASIMHAN",
      "party": "Independent",
      "evm_votes": 77,
      "postal_votes": 3,
      "total_votes": 80
    },
    {
      "name": "BADRI S",
      "party": "Independent",
      "evm_votes": 42,
      "postal_votes": 21,
      "total_votes": 63
    },
    {
      "name": "BALAJI S",
      "party": "Independent",
      "evm_votes": 19,
      "postal_votes": 3,
      "total_votes": 22
    },
    {
      "name": "PRASATH D",
      "party": "Independent",
      "evm_votes": 32,
      "postal_votes": 1,
      "total_votes": 33
    },
    {
      "name": "MANIKANDAN T",
      "party": "Independent",
      "evm_votes": 21,
      "postal_votes": 0,
      "total_votes": 21
    },
    {
      "name": "MANIKANDAN N",
      "party": "Independent",
      "evm_votes": 54,
      "postal_votes": 3,
      "total_votes": 57
    },
    {
      "name": "MOORTHY N",
      "party": "Independent",
      "evm_votes": 43,
      "postal_votes": 6,
      "total_votes": 49
    },
    {
      "name": "MYTHILI C",
      "party": "Independent",
      "evm_votes": 60,
      "postal_votes": 2,
      "total_votes": 62
    },
    {
      "name": "RAMKUMAR L",
      "party": "Independent",
      "evm_votes": 24,
      "postal_votes": 0,
      "total_votes": 24
    },
    {
      "name": "RAMACHANDRAN O N",
      "party": "Independent",
      "evm_votes": 53,
      "postal_votes": 0,
      "total_votes": 53
    },
    {
      "name": "RAJESH E",
      "party": "Independent",
      "evm_votes": 47,
      "postal_votes": 3,
      "total_votes": 50
    },
    {
      "name": "VETRIVEL K",
      "party": "Independent",
      "evm_votes": 60,
      "postal_votes": 3,
      "total_votes": 63
    },
    {
      "name": "JAYAVEL",
      "party": "Independent",
      "evm_votes": 17,
      "postal_votes": 1,
      "total_votes": 18
    },
    {
      "name": "JOTHIRAJ G M",
      "party": "Independent",
      "evm_votes": 12,
      "postal_votes": 1,
      "total_votes": 13
    },
    {
      "name": "NOTA",
      "party": "None of the Above",
      "evm_votes": 588,
      "postal_votes": 53,
      "total_votes": 641
    }
  ]
}