{
  "round": 1,
  "candidates": [
    {
      "name": "SRINIVASAN.P.S",
      "party": "Dravida Munnetra Kazhagam",
      "evm_votes": 0,
      "postal_votes": 3135,
      "total_votes": 3135
    },
    {
      "name": "NAGARAJ.R",
      "party": "Naam Tamilar Katchi",
      "evm_votes": 0,
      "postal_votes": 88,
      "total_votes": 88
    },
    {
      "name": "MUNUSAMY.K.P",
      "party": "All India Anna Dravida Munnetra Kazhagam",
      "evm_votes": 0,
      "postal_votes": 3918,
      "total_votes": 3918
    },
    {
      "name": "IYAPPAN.L",
      "party": "Tamizhaga Vaazhvurimai Katchi",
      "evm_votes": 0,
      "postal_votes": 32,
      "total_votes": 32
    },
    {
      "name": "SAMPANGI.S.R",
      "party": "Tamilaga Vettri Kazhagam",
      "evm_votes": 0,
      "postal_votes": 1278,
      "total_votes": 1278
    },
    {
      "name": "SENTHILKUMAR.R",
      "party": "Tamil Nadu Ilangyar Katchi",
      "evm_votes": 0,
      "postal_votes": 7,
      "total_votes": 7
    },
    {
      "name": "PRAJAPATHI VIJAY.C",
      "party": "Tamilar Makkal Katchi",
      "evm_votes": 0,
      "postal_votes": 4,
      "total_votes": 4
    },
    {
      "name": "ESHWARAN.C",
      "party": "Independent",
      "evm_votes": 0,
      "postal_votes": 7,
      "total_votes": 7
    },
    {
      "name": "GOVINDARAJ.G.J",
      "party": "Independent",
      "evm_votes": 0,
      "postal_votes": 6,
      "total_votes": 6
    },
    {
      "name": "MANOHARAN.K.A",
      "party": "Independent",
      "evm_votes": 0,
      "postal_votes": 9,
      "total_votes": 9
    },
    {
      "name": "YUVARAJ.K.P.U",
      "party": "Independent",
      "evm_votes": 0,
      "postal_votes": 9,
      "total_votes": 9
    },
    {
      "name": "RAMASAMY.G.C",
      "party": "Independent",
      "evm_votes": 0,
      "postal_votes": 32,
      "total_votes": 32
    },
    {
      "name": "VENKATESAN.C",
      "party": "Independent",
      "evm_votes": 0,
      "postal_votes": 35,
      "total_votes": 35
    },
    {
      "name": "NOTA",
      "party": "None of the Above",
      "evm_votes": 0,
      "postal_votes": 56,
      "total_votes": 56
    }
  ]
}